{
  "$schema": "https://json.schemastore.org/tsconfig",
  "extends": "./base.json",
  "Display": "Vite",
  "compilerOptions": {
    "allowJs": false,
    "esModuleInterop": false,
    "module": "ESNext",
    "noEmit": true,
    "resolveJsonModule": true,
    "skipLibCheck": true,
    "target": "ESNext",
    "types": ["vite/client"],
    "useDefineForClassFields": true,
    "lib": ["DOM", "DOM.Iterable", "ESNext"],
    "allowSyntheticDefaultImports": true,
    "strict": true,
    "forceConsistentCasingInFileNames": true,
    "moduleResolution": "Node",
    "isolatedModules": true,
    "jsx": "react-jsx"
  },
  "include": ["src"],
  "references": [{ "path": "./tsconfig.node.json" }]
}
